Metadata-Version: 2.1
Name: wsebas-attackoftheorcs
Version: 2.0.1
Summary: Updated fantasy game
Home-page: https://pypi.org/project/wsebas_attackoftheorcs/
Author: William
Author-email: william@gmail.com
License: LICENSE.txt
Platform: UNKNOWN
